partons-0.0.1.dist-info/METADATA
partons-0.0.1.dist-info/WHEEL
partons/__init__.py
partons/partons.cpython-310-x86_64-linux-gnu.so
partons-0.0.1.dist-info/RECORD
